fast_nbconvert/__init__.py
fast_nbconvert/fast_nbconvert
fast_nbconvert/fast_nbconvert.py
fast_nbconvert-0.1.3.dist-info/entry_points.txt
fast_nbconvert-0.1.3.dist-info/WHEEL
fast_nbconvert-0.1.3.dist-info/METADATA
fast_nbconvert-0.1.3.dist-info/RECORD
