Metadata-Version: 2.1
Name: fast-nbconvert
Version: 0.1.3
Summary: Blazingly fast jupyter notebook to python converter
Author: Davi Suga
Author-email: daviciencia1@gmail.com
Requires-Python: >=3.8,<4.0
Classifier: Programming Language :: Python :: 3
Classifier: Programming Language :: Python :: 3.10
Classifier: Programming Language :: Python :: 3.8
Classifier: Programming Language :: Python :: 3.9
